[
  {
    "nome": "Cerveja Nome 1",
    "descricao": "Descrição da cerveja 1",
    "nomeCervejaria": "Nome da cervejaria",
    "tipo": "PILSEN"
  },
  {
    "nome": "Cerveja Nome 2",
    "descricao": "Descrição da cerveja 1",
    "nomeCervejaria": "Nome da cervejaria",
    "tipo": "PILSEN"
  },
  {
    "nome": "Cerveja Nome 3",
    "descricao": "Descrição da cerveja 1",
    "nomeCervejaria": "Nome da cervejaria",
    "tipo": "PILSEN"
  },
  {
    "nome": "Cerveja Nome 4",
    "descricao": "Descrição da cerveja 1",
    "nomeCervejaria": "Nome da cervejaria",
    "tipo": "PILSEN"
  },
  {
    "nome": "Cerveja Nome 5",
    "descricao": "Descrição da cerveja 1",
    "nomeCervejaria": "Nome da cervejaria",
    "tipo": "PILSEN"
  },
  {
    "nome": "Cerveja Nome 6",
    "descricao": "Descrição da cerveja 1",
    "nomeCervejaria": "Nome da cervejaria",
    "tipo": "PILSEN"
  },
  {
    "nome": "Cerveja Nome 7",
    "descricao": "Descrição da cerveja 1",
    "nomeCervejaria": "Nome da cervejaria",
    "tipo": "PILSEN"
  },
  {
    "nome": "Cerveja Nome 8",
    "descricao": "Descrição da cerveja 1",
    "nomeCervejaria": "Nome da cervejaria",
    "tipo": "PILSEN"
  },
  {
    "nome": "Cerveja Nome 9",
    "descricao": "Descrição da cerveja 1",
    "nomeCervejaria": "Nome da cervejaria",
    "tipo": "PILSEN"
  },
  {
    "nome": "Cerveja Nome 10",
    "descricao": "Descrição da cerveja 1",
    "nomeCervejaria": "Nome da cervejaria",
    "tipo": "PILSEN"
  },
  {
    "nome": "Cerveja Nome 11",
    "descricao": "Descrição da cerveja 1",
    "nomeCervejaria": "Nome da cervejaria",
    "tipo": "PILSEN"
  }
]